dott_ng-1.21.3.dist-info/licenses/LICENSE.txt
dottmi/__init__.py
dottmi/breakpoint.py
dottmi/breakpointhandler.py
dottmi/dott.py
dottmi/dott_conf.py
dottmi/dottexceptions.py
dottmi/fixtures.py
dottmi/gdb.py
dottmi/gdb_cmds.py
dottmi/gdb_mi.py
dottmi/gdb_shared.py
dottmi/gdbcontrollerdott.py
dottmi/monitor.py
dottmi/pylinkdott.py
dottmi/reg_access.py
dottmi/svd2dott.py
dottmi/symbols.py
dottmi/target.py
dottmi/target_mem.py
dottmi/utils.py
dott_ng-1.21.3.dist-info/METADATA
dott_ng-1.21.3.dist-info/WHEEL
dott_ng-1.21.3.dist-info/entry_points.txt
dott_ng-1.21.3.dist-info/top_level.txt
dott_ng-1.21.3.dist-info/RECORD
