Metadata-Version: 2.4
Name: dott-ng
Version: 1.21.3
Summary: Debugger-based on Target Testing (DOTT)
Home-page: https://github.com/tw-ghub/dott-ng
Author: Thomas Winkler
Author-email: thomas.winkler@gmail.com
Classifier: Environment :: Console
Classifier: License :: OSI Approved :: Apache Software License
Classifier: Topic :: Software Development :: Testing
Classifier: Topic :: Software Development :: Debuggers
Classifier: Topic :: Software Development :: Embedded Systems
Requires-Python: >=3.10
License-File: LICENSE.txt
Requires-Dist: dott-ng-runtime==2.13.*,>=1.1.2
Requires-Dist: pygdbmi==0.11.0.0
Requires-Dist: pylink-square<2.0,>=1.0
Requires-Dist: psutil>=6.0.0
Requires-Dist: pytest
Requires-Dist: pytest-cov
Requires-Dist: pytest-instafail
Requires-Dist: pytest-repeat
Requires-Dist: pigpio
Requires-Dist: matplotlib
Requires-Dist: lxml
Dynamic: author
Dynamic: author-email
Dynamic: classifier
Dynamic: description-content-type
Dynamic: home-page
Dynamic: license-file
Dynamic: requires-dist
Dynamic: requires-python
Dynamic: summary
